LICENSE
MANIFEST.in
README.md
pyproject.toml
setup.py
csrc/grouped_gemm.cu
csrc/grouped_gemm.h
csrc/ops.cu
csrc/permute.cu
csrc/permute.h
csrc/sinkhorn.cu
csrc/sinkhorn.h
grouped_gemm/__init__.py
grouped_gemm/backend.py
grouped_gemm/ops.py
grouped_gemm/ops_test.py
grouped_gemm/permute_test.py
grouped_gemm/sinkhorn_test.py
nv_grouped_gemm.egg-info/PKG-INFO
nv_grouped_gemm.egg-info/SOURCES.txt
nv_grouped_gemm.egg-info/dependency_links.txt
nv_grouped_gemm.egg-info/requires.txt
nv_grouped_gemm.egg-info/top_level.txt