Metadata-Version: 2.2
Name: nv_grouped_gemm
Version: 1.1.4.post6
Summary: GEMM Grouped
Home-page: https://github.com/fanshiqing/grouped_gemm
Author: Trevor Gale, Jiang Shao, Shiqing Fan
Author-email: tgale@stanford.edu, jiangs@nvidia.com, shiqingf@nvidia.com
Classifier: Programming Language :: Python :: 3
Classifier: License :: OSI Approved :: BSD License
Classifier: Operating System :: Unix
License-File: LICENSE
Requires-Dist: absl-py
Requires-Dist: numpy
Requires-Dist: torch
Dynamic: author
Dynamic: author-email
Dynamic: classifier
Dynamic: description
Dynamic: description-content-type
Dynamic: home-page
Dynamic: requires-dist
Dynamic: summary
